phishing_detection_py/__init__.py
phishing_detection_py/batch_processor.py
phishing_detection_py/cli.py
phishing_detection_py/config.py
phishing_detection_py/detector.py
phishing_detection_py/logger.py
phishing_detection_py/model_registry.py
phishing_detection_py/preprocessor.py
phishing_detection_py/utils.py
phishing_detection_py-0.1.6.dist-info/LICENSE
phishing_detection_py-0.1.6.dist-info/METADATA
phishing_detection_py-0.1.6.dist-info/WHEEL
phishing_detection_py-0.1.6.dist-info/top_level.txt
phishing_detection_py-0.1.6.dist-info/RECORD
