Metadata-Version: 2.1
Name: phishing-detection-py
Version: 0.1.6
Summary: A Python library for phishing detection using machine learning models.
Home-page: https://github.com/cmacha2/phishing-detection-py
Author: cmacha2
Author-email: cmacha2 <cristiancmg127@gmail.com>
License: Apache-2.0
License-File: LICENSE
Requires-Dist: transformers
Requires-Dist: scikit-learn
Requires-Dist: pandas
Requires-Dist: numpy
Requires-Dist: imblearn
